gamium/__init__.py
gamium/__main__.py
gamium/actions/action_chain.py
gamium/actions/key_by.py
gamium/condition/condition.py
gamium/condition/until.py
gamium/condition/wait_condition.py
gamium/errors/gamium_error.py
gamium/gamium_client.py
gamium/igamium_client.py
gamium/igamium_service.py
gamium/internal/__init__.py
gamium/internal/logger.py
gamium/internal/size_prefixed_recv_queue.py
gamium/locator/by.py
gamium/locator/locator.py
gamium/locator/rpc_by.py
gamium/locator/rpc_locator.py
gamium/object/player.py
gamium/object/ui_element.py
gamium/options/__init__.py
gamium/options/action_click_options.py
gamium/options/action_drag_options.py
gamium/options/action_move_options.py
gamium/options/action_scroll_options.py
gamium/options/execute_rpc_options.py
gamium/options/find_objects_options.py
gamium/options/move_player_options.py
gamium/options/query_object_interactable_options.py
gamium/options/send_key_options.py
gamium/options/set_text_options.py
gamium/options/wait_options.py
gamium/protocol/__init__.py
gamium/protocol/functions.py
gamium/protocol/generated/__init__.py
gamium/protocol/generated/Packets/__init__.py
gamium/protocol/generated/Packets/ActionParam.py
gamium/protocol/generated/Packets/ActionParamSingle.py
gamium/protocol/generated/Packets/ActionResult.py
gamium/protocol/generated/Packets/Actions/__init__.py
gamium/protocol/generated/Packets/Actions/AppQuitParam.py
gamium/protocol/generated/Packets/Actions/InputKeyParam.py
gamium/protocol/generated/Packets/Actions/InputMouseParam.py
gamium/protocol/generated/Packets/Actions/InputSetTextParam.py
gamium/protocol/generated/Packets/Actions/MovePlayerBy.py
gamium/protocol/generated/Packets/Actions/MovePlayerParam.py
gamium/protocol/generated/Packets/Actions/SleepParam.py
gamium/protocol/generated/Packets/ActionsParam.py
gamium/protocol/generated/Packets/ActionsResult.py
gamium/protocol/generated/Packets/ChangeConfigurationParam.py
gamium/protocol/generated/Packets/ChangeConfigurationResult.py
gamium-2.0.10.dist-info/METADATA
gamium-2.0.10.dist-info/WHEEL
gamium-2.0.10.dist-info/RECORD
