Metadata-Version: 2.1
Name: gamium
Version: 2.0.10
Summary: 
Author: dogu
Requires-Python: >=3.9,<4.0
Classifier: Programming Language :: Python :: 3
Classifier: Programming Language :: Python :: 3.9
Classifier: Programming Language :: Python :: 3.10
Classifier: Programming Language :: Python :: 3.11
Classifier: Programming Language :: Python :: 3.12
Requires-Dist: flatbuffers (==22.10.26)
Requires-Dist: numpy (>=1.24.0,<2.0.0)
Requires-Dist: websockets (>=11.0.3,<12.0.0)
